whatsappchat2dataframe/__init__.py
whatsappchat2dataframe/chat2dataframe.py
whatsappchat2dataframe-0.0.4.dist-info/LICENCE
whatsappchat2dataframe-0.0.4.dist-info/METADATA
whatsappchat2dataframe-0.0.4.dist-info/WHEEL
whatsappchat2dataframe-0.0.4.dist-info/top_level.txt
whatsappchat2dataframe-0.0.4.dist-info/RECORD
