Metadata-Version: 2.1
Name: whatsappchat2dataframe
Version: 0.0.4
Summary: Converts a Whatsapp chat (.txt file) into a pandas DataFrame
Author: Kiran Busch
Author-email: <kiranbusch@t-online.de>
Keywords: python,whatsapp
Classifier: Development Status :: 1 - Planning
Classifier: Intended Audience :: Developers
Classifier: Programming Language :: Python :: 3
Classifier: Operating System :: Unix
Classifier: Operating System :: MacOS :: MacOS X
Classifier: Operating System :: Microsoft :: Windows
License-File: LICENCE
Requires-Dist: tqdm
Requires-Dist: regex
Requires-Dist: pandas
